rbnet/__init__.py
rbnet/base.py
rbnet/multivariate_normal.py
rbnet/pcfg.py
rbnet/util.py
rbnet-0.0.1.dist-info/LICENSE
rbnet-0.0.1.dist-info/METADATA
rbnet-0.0.1.dist-info/WHEEL
rbnet-0.0.1.dist-info/top_level.txt
rbnet-0.0.1.dist-info/RECORD
