Metadata-Version: 2.1
Name: rbnet
Version: 0.0.1
Summary: Python implementation of Recursive Bayesian Networks
Home-page: https://github.com/robert-lieck/RBN
Author: Robert Lieck
Author-email: robert.lieck@durham.ac.uk
Classifier: Programming Language :: Python :: 3
Classifier: License :: OSI Approved :: GNU General Public License v3 (GPLv3)
Classifier: Operating System :: OS Independent
Requires-Python: >=3.9
License-File: LICENSE
Requires-Dist: numpy
Requires-Dist: triangularmap
Requires-Dist: torch
